MANIFEST.in
README.md
requirements.txt
setup.cfg
setup.py
hermione/__init__.py
hermione/horizonplot.py
hermione.egg-info/PKG-INFO
hermione.egg-info/SOURCES.txt
hermione.egg-info/dependency_links.txt
hermione.egg-info/requires.txt
hermione.egg-info/top_level.txt