Metadata-Version: 1.0
Name: hermione
Version: 0.1.1
Summary: Joyplots in Python with seaborn-style interface
Home-page: https://github.com/czbiohub/hermione
Author: Olga Botvinnik
Author-email: olga.botvinnik@gmail.com
License: MIT
Platform: UNKNOWN
